CODE_OF_CONDUCT.md
LICENSE
MANIFEST
README.md
setup.py
.github/ISSUE_TEMPLATE/bug_report.md
.github/ISSUE_TEMPLATE/custom.md
.github/ISSUE_TEMPLATE/feature_request.md
CLamPy/__init__.py
CLamPy/clt.py
CLamPy.egg-info/PKG-INFO
CLamPy.egg-info/SOURCES.txt
CLamPy.egg-info/dependency_links.txt
CLamPy.egg-info/top_level.txt
figures/CLamPy.png
figures/CLamPy.svg
test/SimpleTest.ipynb
test/test1.py
test/test2.py