Metadata-Version: 2.1
Name: CLamPy
Version: 1.1
Summary: Classical LAMinate theory for the lightweight design of structures and systems in PYthon
Home-page: UNKNOWN
Author: E. M. Gioia & E. J. Wehrle
License: GNU Lesser General Public License
Platform: UNKNOWN
License-File: LICENSE
